thermochemistry_step/__init__.py
thermochemistry_step/_version.py
thermochemistry_step/metadata.py
thermochemistry_step/thermochemistry.py
thermochemistry_step/thermochemistry_parameters.py
thermochemistry_step/thermochemistry_step.py
thermochemistry_step/tk_thermochemistry.py
thermochemistry_step/data/properties.csv
thermochemistry_step/data/references.bib
thermochemistry_step-2025.1.31.dist-info/AUTHORS.rst
thermochemistry_step-2025.1.31.dist-info/LICENSE
thermochemistry_step-2025.1.31.dist-info/METADATA
thermochemistry_step-2025.1.31.dist-info/WHEEL
thermochemistry_step-2025.1.31.dist-info/entry_points.txt
thermochemistry_step-2025.1.31.dist-info/top_level.txt
thermochemistry_step-2025.1.31.dist-info/zip-safe
thermochemistry_step-2025.1.31.dist-info/RECORD
