Metadata-Version: 2.2
Name: thermochemistry_step
Version: 2025.1.31
Summary: A SEAMM plug-in for Thermochemistry
Home-page: https://github.com/molssi-seamm/thermochemistry_step
Author: Paul Saxe
Author-email: psaxe@molssi.org
License: BSD-3-Clause
Keywords: SEAMM,SEAMMplugin,flowchart
Platform: Linux
Platform: Mac OS-X
Platform: Unix
Platform: Windows
Classifier: Environment :: Plugins
Classifier: Development Status :: 2 - Pre-Alpha
Classifier: Intended Audience :: Science/Research
Classifier: Topic :: Scientific/Engineering :: Chemistry
Classifier: Topic :: Scientific/Engineering :: Physics
Classifier: License :: OSI Approved :: BSD License
Classifier: Natural Language :: English
Classifier: Programming Language :: Python :: 3 :: Only
Classifier: Programming Language :: Python :: 3.8
Classifier: Programming Language :: Python :: 3.9
License-File: LICENSE
License-File: AUTHORS.rst
Requires-Dist: ase
Requires-Dist: molsystem
Requires-Dist: numpy
Requires-Dist: seamm
Requires-Dist: seamm_ase
Requires-Dist: seamm_util
Requires-Dist: seamm_widgets
Requires-Dist: tabulate
Dynamic: author
Dynamic: author-email
Dynamic: classifier
Dynamic: description
Dynamic: description-content-type
Dynamic: home-page
Dynamic: keywords
Dynamic: license
Dynamic: platform
Dynamic: requires-dist
Dynamic: summary
